trytond/modules/webdav/__init__.py
trytond/modules/webdav/protocol.py
trytond/modules/webdav/server.py
trytond/modules/webdav/tryton.cfg
trytond/modules/webdav/webdav.py
trytond/modules/webdav/webdav.xml
trytond/modules/webdav/locale/bg.po
trytond/modules/webdav/locale/ca.po
trytond/modules/webdav/locale/cs.po
trytond/modules/webdav/locale/de.po
trytond/modules/webdav/locale/es.po
trytond/modules/webdav/locale/es_419.po
trytond/modules/webdav/locale/fr.po
trytond/modules/webdav/locale/hu_HU.po
trytond/modules/webdav/locale/it_IT.po
trytond/modules/webdav/locale/ja_JP.po
trytond/modules/webdav/locale/lo.po
trytond/modules/webdav/locale/lt.po
trytond/modules/webdav/locale/nl.po
trytond/modules/webdav/locale/pl.po
trytond/modules/webdav/locale/pt_BR.po
trytond/modules/webdav/locale/ru.po
trytond/modules/webdav/locale/sl.po
trytond/modules/webdav/locale/zh_CN.po
trytond/modules/webdav/tests/__init__.py
trytond/modules/webdav/tests/test_webdav.py
trytond/modules/webdav/view/attachment_form.xml
trytond/modules/webdav/view/collection_form.xml
trytond/modules/webdav/view/collection_list.xml
trytond/modules/webdav/view/collection_tree.xml
trytond/modules/webdav/view/share_form.xml
trytond/modules/webdav/view/share_list.xml
trytond_webdav-4.2.1.data/scripts/trytond-webdav
trytond_webdav-4.2.1.dist-info/DESCRIPTION.rst
trytond_webdav-4.2.1.dist-info/METADATA
trytond_webdav-4.2.1.dist-info/RECORD
trytond_webdav-4.2.1.dist-info/WHEEL
trytond_webdav-4.2.1.dist-info/entry_points.txt
trytond_webdav-4.2.1.dist-info/metadata.json
trytond_webdav-4.2.1.dist-info/top_level.txt
